statsql/__init__.py
statsql-0.0.0.dist-info/METADATA
statsql-0.0.0.dist-info/WHEEL
statsql-0.0.0.dist-info/top_level.txt
statsql-0.0.0.dist-info/RECORD
